<?xml version="1.0" encoding="UTF-8"?>
<!DOCTYPE QtCreatorToolChains>
<!-- Written by QtCreator 4.5.2, 2020-02-20T10:47:09. -->
<qtcreator>
 <data>
  <variable>ToolChain.0</variable>
  <valuemap type="QVariantMap">
   <value type="QString" key="ProjectExplorer.GccToolChain.OriginalTargetTriple">x86_64-linux-gnu</value>
   <value type="QString" key="ProjectExplorer.GccToolChain.Path">/usr/bin/g++</value>
   <valuelist type="QVariantList" key="ProjectExplorer.GccToolChain.PlatformCodeGenFlags"/>
   <valuelist type="QVariantList" key="ProjectExplorer.GccToolChain.PlatformLinkerFlags"/>
   <valuelist type="QVariantList" key="ProjectExplorer.GccToolChain.SupportedAbis">
    <value type="QString">x86-linux-generic-elf-64bit</value>
    <value type="QString">x86-linux-generic-elf-32bit</value>
   </valuelist>
   <value type="QString" key="ProjectExplorer.GccToolChain.TargetAbi">x86-linux-generic-elf-64bit</value>
   <value type="bool" key="ProjectExplorer.ToolChain.Autodetect">true</value>
   <value type="QString" key="ProjectExplorer.ToolChain.DisplayName">GCC (C++, x86 64bit in /usr/bin)</value>
   <value type="QString" key="ProjectExplorer.ToolChain.Id">ProjectExplorer.ToolChain.Gcc:{de3f5354-e978-49af-ae6c-975249244bec}</value>
   <value type="int" key="ProjectExplorer.ToolChain.Language">2</value>
   <value type="QString" key="ProjectExplorer.ToolChain.LanguageV2">Cxx</value>
  </valuemap>
 </data>
 <data>
  <variable>ToolChain.1</variable>
  <valuemap type="QVariantMap">
   <value type="QString" key="ProjectExplorer.GccToolChain.OriginalTargetTriple">x86_64-linux-gnu</value>
   <value type="QString" key="ProjectExplorer.GccToolChain.Path">/usr/bin/g++</value>
   <valuelist type="QVariantList" key="ProjectExplorer.GccToolChain.PlatformCodeGenFlags"/>
   <valuelist type="QVariantList" key="ProjectExplorer.GccToolChain.PlatformLinkerFlags"/>
   <valuelist type="QVariantList" key="ProjectExplorer.GccToolChain.SupportedAbis">
    <value type="QString">x86-linux-generic-elf-64bit</value>
    <value type="QString">x86-linux-generic-elf-32bit</value>
   </valuelist>
   <value type="QString" key="ProjectExplorer.GccToolChain.TargetAbi">x86-linux-generic-elf-32bit</value>
   <value type="bool" key="ProjectExplorer.ToolChain.Autodetect">true</value>
   <value type="QString" key="ProjectExplorer.ToolChain.DisplayName">GCC (C++, x86 32bit in /usr/bin)</value>
   <value type="QString" key="ProjectExplorer.ToolChain.Id">ProjectExplorer.ToolChain.Gcc:{84147b8a-8608-4da5-aea7-92bf09115f6e}</value>
   <value type="int" key="ProjectExplorer.ToolChain.Language">2</value>
   <value type="QString" key="ProjectExplorer.ToolChain.LanguageV2">Cxx</value>
  </valuemap>
 </data>
 <data>
  <variable>ToolChain.10</variable>
  <valuemap type="QVariantMap">
   <value type="QString" key="ProjectExplorer.GccToolChain.OriginalTargetTriple">x86_64-linux-gnu</value>
   <value type="QString" key="ProjectExplorer.GccToolChain.Path">/usr/bin/gcc-7</value>
   <valuelist type="QVariantList" key="ProjectExplorer.GccToolChain.PlatformCodeGenFlags"/>
   <valuelist type="QVariantList" key="ProjectExplorer.GccToolChain.PlatformLinkerFlags"/>
   <valuelist type="QVariantList" key="ProjectExplorer.GccToolChain.SupportedAbis">
    <value type="QString">x86-linux-generic-elf-64bit</value>
    <value type="QString">x86-linux-generic-elf-32bit</value>
   </valuelist>
   <value type="QString" key="ProjectExplorer.GccToolChain.TargetAbi">x86-linux-generic-elf-64bit</value>
   <value type="bool" key="ProjectExplorer.ToolChain.Autodetect">true</value>
   <value type="QString" key="ProjectExplorer.ToolChain.DisplayName">GCC 7 (C, x86 64bit in /usr/bin)</value>
   <value type="QString" key="ProjectExplorer.ToolChain.Id">ProjectExplorer.ToolChain.Gcc:{86358d28-c6a6-4a06-89a5-b0dee407dd47}</value>
   <value type="int" key="ProjectExplorer.ToolChain.Language">1</value>
   <value type="QString" key="ProjectExplorer.ToolChain.LanguageV2">C</value>
  </valuemap>
 </data>
 <data>
  <variable>ToolChain.11</variable>
  <valuemap type="QVariantMap">
   <value type="QString" key="ProjectExplorer.GccToolChain.OriginalTargetTriple">x86_64-linux-gnu</value>
   <value type="QString" key="ProjectExplorer.GccToolChain.Path">/usr/bin/gcc-7</value>
   <valuelist type="QVariantList" key="ProjectExplorer.GccToolChain.PlatformCodeGenFlags"/>
   <valuelist type="QVariantList" key="ProjectExplorer.GccToolChain.PlatformLinkerFlags"/>
   <valuelist type="QVariantList" key="ProjectExplorer.GccToolChain.SupportedAbis">
    <value type="QString">x86-linux-generic-elf-64bit</value>
    <value type="QString">x86-linux-generic-elf-32bit</value>
   </valuelist>
   <value type="QString" key="ProjectExplorer.GccToolChain.TargetAbi">x86-linux-generic-elf-32bit</value>
   <value type="bool" key="ProjectExplorer.ToolChain.Autodetect">true</value>
   <value type="QString" key="ProjectExplorer.ToolChain.DisplayName">GCC 7 (C, x86 32bit in /usr/bin)</value>
   <value type="QString" key="ProjectExplorer.ToolChain.Id">ProjectExplorer.ToolChain.Gcc:{78788c40-e351-4f82-a052-803c34bbbfc5}</value>
   <value type="int" key="ProjectExplorer.ToolChain.Language">1</value>
   <value type="QString" key="ProjectExplorer.ToolChain.LanguageV2">C</value>
  </valuemap>
 </data>
 <data>
  <variable>ToolChain.12</variable>
  <valuemap type="QVariantMap">
   <value type="QString" key="ProjectExplorer.GccToolChain.OriginalTargetTriple">x86_64-linux-gnu</value>
   <value type="QString" key="ProjectExplorer.GccToolChain.Path">/usr/bin/x86_64-linux-gnu-gcc</value>
   <valuelist type="QVariantList" key="ProjectExplorer.GccToolChain.PlatformCodeGenFlags"/>
   <valuelist type="QVariantList" key="ProjectExplorer.GccToolChain.PlatformLinkerFlags"/>
   <valuelist type="QVariantList" key="ProjectExplorer.GccToolChain.SupportedAbis">
    <value type="QString">x86-linux-generic-elf-64bit</value>
    <value type="QString">x86-linux-generic-elf-32bit</value>
   </valuelist>
   <value type="QString" key="ProjectExplorer.GccToolChain.TargetAbi">x86-linux-generic-elf-64bit</value>
   <value type="bool" key="ProjectExplorer.ToolChain.Autodetect">true</value>
   <value type="QString" key="ProjectExplorer.ToolChain.DisplayName">GCC (C, x86 64bit in /usr/bin)</value>
   <value type="QString" key="ProjectExplorer.ToolChain.Id">ProjectExplorer.ToolChain.Gcc:{425df9d9-a5f2-4b2e-a439-f2161bc85a2d}</value>
   <value type="int" key="ProjectExplorer.ToolChain.Language">1</value>
   <value type="QString" key="ProjectExplorer.ToolChain.LanguageV2">C</value>
  </valuemap>
 </data>
 <data>
  <variable>ToolChain.13</variable>
  <valuemap type="QVariantMap">
   <value type="QString" key="ProjectExplorer.GccToolChain.OriginalTargetTriple">x86_64-linux-gnu</value>
   <value type="QString" key="ProjectExplorer.GccToolChain.Path">/usr/bin/x86_64-linux-gnu-gcc</value>
   <valuelist type="QVariantList" key="ProjectExplorer.GccToolChain.PlatformCodeGenFlags"/>
   <valuelist type="QVariantList" key="ProjectExplorer.GccToolChain.PlatformLinkerFlags"/>
   <valuelist type="QVariantList" key="ProjectExplorer.GccToolChain.SupportedAbis">
    <value type="QString">x86-linux-generic-elf-64bit</value>
    <value type="QString">x86-linux-generic-elf-32bit</value>
   </valuelist>
   <value type="QString" key="ProjectExplorer.GccToolChain.TargetAbi">x86-linux-generic-elf-32bit</value>
   <value type="bool" key="ProjectExplorer.ToolChain.Autodetect">true</value>
   <value type="QString" key="ProjectExplorer.ToolChain.DisplayName">GCC (C, x86 32bit in /usr/bin)</value>
   <value type="QString" key="ProjectExplorer.ToolChain.Id">ProjectExplorer.ToolChain.Gcc:{aec5aba2-a943-46c3-b241-986c475dd642}</value>
   <value type="int" key="ProjectExplorer.ToolChain.Language">1</value>
   <value type="QString" key="ProjectExplorer.ToolChain.LanguageV2">C</value>
  </valuemap>
 </data>
 <data>
  <variable>ToolChain.14</variable>
  <valuemap type="QVariantMap">
   <value type="QString" key="ProjectExplorer.GccToolChain.OriginalTargetTriple">x86_64-linux-gnu</value>
   <value type="QString" key="ProjectExplorer.GccToolChain.Path">/usr/bin/x86_64-linux-gnu-gcc-7</value>
   <valuelist type="QVariantList" key="ProjectExplorer.GccToolChain.PlatformCodeGenFlags"/>
   <valuelist type="QVariantList" key="ProjectExplorer.GccToolChain.PlatformLinkerFlags"/>
   <valuelist type="QVariantList" key="ProjectExplorer.GccToolChain.SupportedAbis">
    <value type="QString">x86-linux-generic-elf-64bit</value>
    <value type="QString">x86-linux-generic-elf-32bit</value>
   </valuelist>
   <value type="QString" key="ProjectExplorer.GccToolChain.TargetAbi">x86-linux-generic-elf-64bit</value>
   <value type="bool" key="ProjectExplorer.ToolChain.Autodetect">true</value>
   <value type="QString" key="ProjectExplorer.ToolChain.DisplayName">GCC 7 (C, x86 64bit in /usr/bin)</value>
   <value type="QString" key="ProjectExplorer.ToolChain.Id">ProjectExplorer.ToolChain.Gcc:{67f3f749-c845-4469-b5f6-a80c13454dcd}</value>
   <value type="int" key="ProjectExplorer.ToolChain.Language">1</value>
   <value type="QString" key="ProjectExplorer.ToolChain.LanguageV2">C</value>
  </valuemap>
 </data>
 <data>
  <variable>ToolChain.15</variable>
  <valuemap type="QVariantMap">
   <value type="QString" key="ProjectExplorer.GccToolChain.OriginalTargetTriple">x86_64-linux-gnu</value>
   <value type="QString" key="ProjectExplorer.GccToolChain.Path">/usr/bin/x86_64-linux-gnu-gcc-7</value>
   <valuelist type="QVariantList" key="ProjectExplorer.GccToolChain.PlatformCodeGenFlags"/>
   <valuelist type="QVariantList" key="ProjectExplorer.GccToolChain.PlatformLinkerFlags"/>
   <valuelist type="QVariantList" key="ProjectExplorer.GccToolChain.SupportedAbis">
    <value type="QString">x86-linux-generic-elf-64bit</value>
    <value type="QString">x86-linux-generic-elf-32bit</value>
   </valuelist>
   <value type="QString" key="ProjectExplorer.GccToolChain.TargetAbi">x86-linux-generic-elf-32bit</value>
   <value type="bool" key="ProjectExplorer.ToolChain.Autodetect">true</value>
   <value type="QString" key="ProjectExplorer.ToolChain.DisplayName">GCC 7 (C, x86 32bit in /usr/bin)</value>
   <value type="QString" key="ProjectExplorer.ToolChain.Id">ProjectExplorer.ToolChain.Gcc:{43e7ed74-2c9d-4783-a2c2-789a59e49dd2}</value>
   <value type="int" key="ProjectExplorer.ToolChain.Language">1</value>
   <value type="QString" key="ProjectExplorer.ToolChain.LanguageV2">C</value>
  </valuemap>
 </data>
 <data>
  <variable>ToolChain.16</variable>
  <valuemap type="QVariantMap">
   <value type="QString" key="ProjectExplorer.GccToolChain.OriginalTargetTriple">x86_64-pc-linux-gnu</value>
   <value type="QString" key="ProjectExplorer.GccToolChain.Path">/usr/bin/clang++</value>
   <valuelist type="QVariantList" key="ProjectExplorer.GccToolChain.PlatformCodeGenFlags"/>
   <valuelist type="QVariantList" key="ProjectExplorer.GccToolChain.PlatformLinkerFlags"/>
   <valuelist type="QVariantList" key="ProjectExplorer.GccToolChain.SupportedAbis">
    <value type="QString">x86-linux-generic-elf-64bit</value>
    <value type="QString">x86-linux-generic-elf-32bit</value>
   </valuelist>
   <value type="QString" key="ProjectExplorer.GccToolChain.TargetAbi">x86-linux-generic-elf-64bit</value>
   <value type="bool" key="ProjectExplorer.ToolChain.Autodetect">true</value>
   <value type="QString" key="ProjectExplorer.ToolChain.DisplayName">Clang (C++, x86 64bit in /usr/bin)</value>
   <value type="QString" key="ProjectExplorer.ToolChain.Id">ProjectExplorer.ToolChain.Clang:{232d38f4-03ac-42ac-b157-4af7ca9c9f48}</value>
   <value type="int" key="ProjectExplorer.ToolChain.Language">2</value>
   <value type="QString" key="ProjectExplorer.ToolChain.LanguageV2">Cxx</value>
  </valuemap>
 </data>
 <data>
  <variable>ToolChain.17</variable>
  <valuemap type="QVariantMap">
   <value type="QString" key="ProjectExplorer.GccToolChain.OriginalTargetTriple">x86_64-pc-linux-gnu</value>
   <value type="QString" key="ProjectExplorer.GccToolChain.Path">/usr/bin/clang++</value>
   <valuelist type="QVariantList" key="ProjectExplorer.GccToolChain.PlatformCodeGenFlags"/>
   <valuelist type="QVariantList" key="ProjectExplorer.GccToolChain.PlatformLinkerFlags"/>
   <valuelist type="QVariantList" key="ProjectExplorer.GccToolChain.SupportedAbis">
    <value type="QString">x86-linux-generic-elf-64bit</value>
    <value type="QString">x86-linux-generic-elf-32bit</value>
   </valuelist>
   <value type="QString" key="ProjectExplorer.GccToolChain.TargetAbi">x86-linux-generic-elf-32bit</value>
   <value type="bool" key="ProjectExplorer.ToolChain.Autodetect">true</value>
   <value type="QString" key="ProjectExplorer.ToolChain.DisplayName">Clang (C++, x86 32bit in /usr/bin)</value>
   <value type="QString" key="ProjectExplorer.ToolChain.Id">ProjectExplorer.ToolChain.Clang:{863fde4f-9ea2-41f2-9c4b-faadb20ad726}</value>
   <value type="int" key="ProjectExplorer.ToolChain.Language">2</value>
   <value type="QString" key="ProjectExplorer.ToolChain.LanguageV2">Cxx</value>
  </valuemap>
 </data>
 <data>
  <variable>ToolChain.18</variable>
  <valuemap type="QVariantMap">
   <value type="QString" key="ProjectExplorer.GccToolChain.OriginalTargetTriple">x86_64-pc-linux-gnu</value>
   <value type="QString" key="ProjectExplorer.GccToolChain.Path">/usr/bin/clang</value>
   <valuelist type="QVariantList" key="ProjectExplorer.GccToolChain.PlatformCodeGenFlags"/>
   <valuelist type="QVariantList" key="ProjectExplorer.GccToolChain.PlatformLinkerFlags"/>
   <valuelist type="QVariantList" key="ProjectExplorer.GccToolChain.SupportedAbis">
    <value type="QString">x86-linux-generic-elf-64bit</value>
    <value type="QString">x86-linux-generic-elf-32bit</value>
   </valuelist>
   <value type="QString" key="ProjectExplorer.GccToolChain.TargetAbi">x86-linux-generic-elf-64bit</value>
   <value type="bool" key="ProjectExplorer.ToolChain.Autodetect">true</value>
   <value type="QString" key="ProjectExplorer.ToolChain.DisplayName">Clang (C, x86 64bit in /usr/bin)</value>
   <value type="QString" key="ProjectExplorer.ToolChain.Id">ProjectExplorer.ToolChain.Clang:{a7c21d6e-0f60-4015-ba01-92d2a6b41601}</value>
   <value type="int" key="ProjectExplorer.ToolChain.Language">1</value>
   <value type="QString" key="ProjectExplorer.ToolChain.LanguageV2">C</value>
  </valuemap>
 </data>
 <data>
  <variable>ToolChain.19</variable>
  <valuemap type="QVariantMap">
   <value type="QString" key="ProjectExplorer.GccToolChain.OriginalTargetTriple">x86_64-pc-linux-gnu</value>
   <value type="QString" key="ProjectExplorer.GccToolChain.Path">/usr/bin/clang</value>
   <valuelist type="QVariantList" key="ProjectExplorer.GccToolChain.PlatformCodeGenFlags"/>
   <valuelist type="QVariantList" key="ProjectExplorer.GccToolChain.PlatformLinkerFlags"/>
   <valuelist type="QVariantList" key="ProjectExplorer.GccToolChain.SupportedAbis">
    <value type="QString">x86-linux-generic-elf-64bit</value>
    <value type="QString">x86-linux-generic-elf-32bit</value>
   </valuelist>
   <value type="QString" key="ProjectExplorer.GccToolChain.TargetAbi">x86-linux-generic-elf-32bit</value>
   <value type="bool" key="ProjectExplorer.ToolChain.Autodetect">true</value>
   <value type="QString" key="ProjectExplorer.ToolChain.DisplayName">Clang (C, x86 32bit in /usr/bin)</value>
   <value type="QString" key="ProjectExplorer.ToolChain.Id">ProjectExplorer.ToolChain.Clang:{c41d5de4-c3bd-42bb-a1cd-db4a0c05dad7}</value>
   <value type="int" key="ProjectExplorer.ToolChain.Language">1</value>
   <value type="QString" key="ProjectExplorer.ToolChain.LanguageV2">C</value>
  </valuemap>
 </data>
 <data>
  <variable>ToolChain.2</variable>
  <valuemap type="QVariantMap">
   <value type="QString" key="ProjectExplorer.GccToolChain.OriginalTargetTriple">x86_64-linux-gnu</value>
   <value type="QString" key="ProjectExplorer.GccToolChain.Path">/usr/bin/gcc</value>
   <valuelist type="QVariantList" key="ProjectExplorer.GccToolChain.PlatformCodeGenFlags"/>
   <valuelist type="QVariantList" key="ProjectExplorer.GccToolChain.PlatformLinkerFlags"/>
   <valuelist type="QVariantList" key="ProjectExplorer.GccToolChain.SupportedAbis">
    <value type="QString">x86-linux-generic-elf-64bit</value>
    <value type="QString">x86-linux-generic-elf-32bit</value>
   </valuelist>
   <value type="QString" key="ProjectExplorer.GccToolChain.TargetAbi">x86-linux-generic-elf-64bit</value>
   <value type="bool" key="ProjectExplorer.ToolChain.Autodetect">true</value>
   <value type="QString" key="ProjectExplorer.ToolChain.DisplayName">GCC (C, x86 64bit in /usr/bin)</value>
   <value type="QString" key="ProjectExplorer.ToolChain.Id">ProjectExplorer.ToolChain.Gcc:{6441dc81-607a-4b7f-8e0c-487403bc9528}</value>
   <value type="int" key="ProjectExplorer.ToolChain.Language">1</value>
   <value type="QString" key="ProjectExplorer.ToolChain.LanguageV2">C</value>
  </valuemap>
 </data>
 <data>
  <variable>ToolChain.3</variable>
  <valuemap type="QVariantMap">
   <value type="QString" key="ProjectExplorer.GccToolChain.OriginalTargetTriple">x86_64-linux-gnu</value>
   <value type="QString" key="ProjectExplorer.GccToolChain.Path">/usr/bin/gcc</value>
   <valuelist type="QVariantList" key="ProjectExplorer.GccToolChain.PlatformCodeGenFlags"/>
   <valuelist type="QVariantList" key="ProjectExplorer.GccToolChain.PlatformLinkerFlags"/>
   <valuelist type="QVariantList" key="ProjectExplorer.GccToolChain.SupportedAbis">
    <value type="QString">x86-linux-generic-elf-64bit</value>
    <value type="QString">x86-linux-generic-elf-32bit</value>
   </valuelist>
   <value type="QString" key="ProjectExplorer.GccToolChain.TargetAbi">x86-linux-generic-elf-32bit</value>
   <value type="bool" key="ProjectExplorer.ToolChain.Autodetect">true</value>
   <value type="QString" key="ProjectExplorer.ToolChain.DisplayName">GCC (C, x86 32bit in /usr/bin)</value>
   <value type="QString" key="ProjectExplorer.ToolChain.Id">ProjectExplorer.ToolChain.Gcc:{adb70014-cb08-46b9-aadb-53f4fa4a6040}</value>
   <value type="int" key="ProjectExplorer.ToolChain.Language">1</value>
   <value type="QString" key="ProjectExplorer.ToolChain.LanguageV2">C</value>
  </valuemap>
 </data>
 <data>
  <variable>ToolChain.4</variable>
  <valuemap type="QVariantMap">
   <value type="QString" key="ProjectExplorer.GccToolChain.OriginalTargetTriple">x86_64-linux-gnu</value>
   <value type="QString" key="ProjectExplorer.GccToolChain.Path">/usr/bin/g++-7</value>
   <valuelist type="QVariantList" key="ProjectExplorer.GccToolChain.PlatformCodeGenFlags"/>
   <valuelist type="QVariantList" key="ProjectExplorer.GccToolChain.PlatformLinkerFlags"/>
   <valuelist type="QVariantList" key="ProjectExplorer.GccToolChain.SupportedAbis">
    <value type="QString">x86-linux-generic-elf-64bit</value>
    <value type="QString">x86-linux-generic-elf-32bit</value>
   </valuelist>
   <value type="QString" key="ProjectExplorer.GccToolChain.TargetAbi">x86-linux-generic-elf-64bit</value>
   <value type="bool" key="ProjectExplorer.ToolChain.Autodetect">true</value>
   <value type="QString" key="ProjectExplorer.ToolChain.DisplayName">GCC 7 (C++, x86 64bit in /usr/bin)</value>
   <value type="QString" key="ProjectExplorer.ToolChain.Id">ProjectExplorer.ToolChain.Gcc:{c080be0e-a984-49ad-bf7c-8f93739e58f2}</value>
   <value type="int" key="ProjectExplorer.ToolChain.Language">2</value>
   <value type="QString" key="ProjectExplorer.ToolChain.LanguageV2">Cxx</value>
  </valuemap>
 </data>
 <data>
  <variable>ToolChain.5</variable>
  <valuemap type="QVariantMap">
   <value type="QString" key="ProjectExplorer.GccToolChain.OriginalTargetTriple">x86_64-linux-gnu</value>
   <value type="QString" key="ProjectExplorer.GccToolChain.Path">/usr/bin/g++-7</value>
   <valuelist type="QVariantList" key="ProjectExplorer.GccToolChain.PlatformCodeGenFlags"/>
   <valuelist type="QVariantList" key="ProjectExplorer.GccToolChain.PlatformLinkerFlags"/>
   <valuelist type="QVariantList" key="ProjectExplorer.GccToolChain.SupportedAbis">
    <value type="QString">x86-linux-generic-elf-64bit</value>
    <value type="QString">x86-linux-generic-elf-32bit</value>
   </valuelist>
   <value type="QString" key="ProjectExplorer.GccToolChain.TargetAbi">x86-linux-generic-elf-32bit</value>
   <value type="bool" key="ProjectExplorer.ToolChain.Autodetect">true</value>
   <value type="QString" key="ProjectExplorer.ToolChain.DisplayName">GCC 7 (C++, x86 32bit in /usr/bin)</value>
   <value type="QString" key="ProjectExplorer.ToolChain.Id">ProjectExplorer.ToolChain.Gcc:{5bc1d427-49d5-4529-ac22-1ed8f7d004a0}</value>
   <value type="int" key="ProjectExplorer.ToolChain.Language">2</value>
   <value type="QString" key="ProjectExplorer.ToolChain.LanguageV2">Cxx</value>
  </valuemap>
 </data>
 <data>
  <variable>ToolChain.6</variable>
  <valuemap type="QVariantMap">
   <value type="QString" key="ProjectExplorer.GccToolChain.OriginalTargetTriple">x86_64-linux-gnu</value>
   <value type="QString" key="ProjectExplorer.GccToolChain.Path">/usr/bin/x86_64-linux-gnu-g++</value>
   <valuelist type="QVariantList" key="ProjectExplorer.GccToolChain.PlatformCodeGenFlags"/>
   <valuelist type="QVariantList" key="ProjectExplorer.GccToolChain.PlatformLinkerFlags"/>
   <valuelist type="QVariantList" key="ProjectExplorer.GccToolChain.SupportedAbis">
    <value type="QString">x86-linux-generic-elf-64bit</value>
    <value type="QString">x86-linux-generic-elf-32bit</value>
   </valuelist>
   <value type="QString" key="ProjectExplorer.GccToolChain.TargetAbi">x86-linux-generic-elf-64bit</value>
   <value type="bool" key="ProjectExplorer.ToolChain.Autodetect">true</value>
   <value type="QString" key="ProjectExplorer.ToolChain.DisplayName">GCC (C++, x86 64bit in /usr/bin)</value>
   <value type="QString" key="ProjectExplorer.ToolChain.Id">ProjectExplorer.ToolChain.Gcc:{bdb64103-769a-428c-8788-277f6451fb72}</value>
   <value type="int" key="ProjectExplorer.ToolChain.Language">2</value>
   <value type="QString" key="ProjectExplorer.ToolChain.LanguageV2">Cxx</value>
  </valuemap>
 </data>
 <data>
  <variable>ToolChain.7</variable>
  <valuemap type="QVariantMap">
   <value type="QString" key="ProjectExplorer.GccToolChain.OriginalTargetTriple">x86_64-linux-gnu</value>
   <value type="QString" key="ProjectExplorer.GccToolChain.Path">/usr/bin/x86_64-linux-gnu-g++</value>
   <valuelist type="QVariantList" key="ProjectExplorer.GccToolChain.PlatformCodeGenFlags"/>
   <valuelist type="QVariantList" key="ProjectExplorer.GccToolChain.PlatformLinkerFlags"/>
   <valuelist type="QVariantList" key="ProjectExplorer.GccToolChain.SupportedAbis">
    <value type="QString">x86-linux-generic-elf-64bit</value>
    <value type="QString">x86-linux-generic-elf-32bit</value>
   </valuelist>
   <value type="QString" key="ProjectExplorer.GccToolChain.TargetAbi">x86-linux-generic-elf-32bit</value>
   <value type="bool" key="ProjectExplorer.ToolChain.Autodetect">true</value>
   <value type="QString" key="ProjectExplorer.ToolChain.DisplayName">GCC (C++, x86 32bit in /usr/bin)</value>
   <value type="QString" key="ProjectExplorer.ToolChain.Id">ProjectExplorer.ToolChain.Gcc:{2674acbb-a9f7-483b-b9e9-a542304386cb}</value>
   <value type="int" key="ProjectExplorer.ToolChain.Language">2</value>
   <value type="QString" key="ProjectExplorer.ToolChain.LanguageV2">Cxx</value>
  </valuemap>
 </data>
 <data>
  <variable>ToolChain.8</variable>
  <valuemap type="QVariantMap">
   <value type="QString" key="ProjectExplorer.GccToolChain.OriginalTargetTriple">x86_64-linux-gnu</value>
   <value type="QString" key="ProjectExplorer.GccToolChain.Path">/usr/bin/x86_64-linux-gnu-g++-7</value>
   <valuelist type="QVariantList" key="ProjectExplorer.GccToolChain.PlatformCodeGenFlags"/>
   <valuelist type="QVariantList" key="ProjectExplorer.GccToolChain.PlatformLinkerFlags"/>
   <valuelist type="QVariantList" key="ProjectExplorer.GccToolChain.SupportedAbis">
    <value type="QString">x86-linux-generic-elf-64bit</value>
    <value type="QString">x86-linux-generic-elf-32bit</value>
   </valuelist>
   <value type="QString" key="ProjectExplorer.GccToolChain.TargetAbi">x86-linux-generic-elf-64bit</value>
   <value type="bool" key="ProjectExplorer.ToolChain.Autodetect">true</value>
   <value type="QString" key="ProjectExplorer.ToolChain.DisplayName">GCC 7 (C++, x86 64bit in /usr/bin)</value>
   <value type="QString" key="ProjectExplorer.ToolChain.Id">ProjectExplorer.ToolChain.Gcc:{9727dc6d-0a5a-4695-ad48-8653205942c8}</value>
   <value type="int" key="ProjectExplorer.ToolChain.Language">2</value>
   <value type="QString" key="ProjectExplorer.ToolChain.LanguageV2">Cxx</value>
  </valuemap>
 </data>
 <data>
  <variable>ToolChain.9</variable>
  <valuemap type="QVariantMap">
   <value type="QString" key="ProjectExplorer.GccToolChain.OriginalTargetTriple">x86_64-linux-gnu</value>
   <value type="QString" key="ProjectExplorer.GccToolChain.Path">/usr/bin/x86_64-linux-gnu-g++-7</value>
   <valuelist type="QVariantList" key="ProjectExplorer.GccToolChain.PlatformCodeGenFlags"/>
   <valuelist type="QVariantList" key="ProjectExplorer.GccToolChain.PlatformLinkerFlags"/>
   <valuelist type="QVariantList" key="ProjectExplorer.GccToolChain.SupportedAbis">
    <value type="QString">x86-linux-generic-elf-64bit</value>
    <value type="QString">x86-linux-generic-elf-32bit</value>
   </valuelist>
   <value type="QString" key="ProjectExplorer.GccToolChain.TargetAbi">x86-linux-generic-elf-32bit</value>
   <value type="bool" key="ProjectExplorer.ToolChain.Autodetect">true</value>
   <value type="QString" key="ProjectExplorer.ToolChain.DisplayName">GCC 7 (C++, x86 32bit in /usr/bin)</value>
   <value type="QString" key="ProjectExplorer.ToolChain.Id">ProjectExplorer.ToolChain.Gcc:{8681728e-eb00-4698-8ae7-e6a607c1b2e3}</value>
   <value type="int" key="ProjectExplorer.ToolChain.Language">2</value>
   <value type="QString" key="ProjectExplorer.ToolChain.LanguageV2">Cxx</value>
  </valuemap>
 </data>
 <data>
  <variable>ToolChain.Count</variable>
  <value type="int">20</value>
 </data>
 <data>
  <variable>Version</variable>
  <value type="int">1</value>
 </data>
</qtcreator>
