<?xml version="1.0" encoding="UTF-8"?>
<!DOCTYPE QtCreatorToolChains>
<!-- Written by QtCreator 4.5.2, 2020-02-20T10:48:33. -->
<qtcreator>
 <data>
  <variable>ToolChain.0</variable>
  <valuemap type="QVariantMap">
   <value type="QString" key="ProjectExplorer.GccToolChain.OriginalTargetTriple">x86_64-linux-gnu</value>
   <value type="QString" key="ProjectExplorer.GccToolChain.Path">/usr/bin/g++</value>
   <valuelist type="QVariantList" key="ProjectExplorer.GccToolChain.PlatformCodeGenFlags"/>
   <valuelist type="QVariantList" key="ProjectExplorer.GccToolChain.PlatformLinkerFlags"/>
   <valuelist type="QVariantList" key="ProjectExplorer.GccToolChain.SupportedAbis">
    <value type="QString">x86-linux-generic-elf-64bit</value>
    <value type="QString">x86-linux-generic-elf-32bit</value>
   </valuelist>
   <value type="QString" key="ProjectExplorer.GccToolChain.TargetAbi">x86-linux-generic-elf-64bit</value>
   <value type="bool" key="ProjectExplorer.ToolChain.Autodetect">true</value>
   <value type="QString" key="ProjectExplorer.ToolChain.DisplayName">GCC (C++, x86 64bit in /usr/bin)</value>
   <value type="QString" key="ProjectExplorer.ToolChain.Id">ProjectExplorer.ToolChain.Gcc:{4699a25a-a81d-44ea-b919-96325f8d8149}</value>
   <value type="int" key="ProjectExplorer.ToolChain.Language">2</value>
   <value type="QString" key="ProjectExplorer.ToolChain.LanguageV2">Cxx</value>
  </valuemap>
 </data>
 <data>
  <variable>ToolChain.1</variable>
  <valuemap type="QVariantMap">
   <value type="QString" key="ProjectExplorer.GccToolChain.OriginalTargetTriple">x86_64-linux-gnu</value>
   <value type="QString" key="ProjectExplorer.GccToolChain.Path">/usr/bin/g++</value>
   <valuelist type="QVariantList" key="ProjectExplorer.GccToolChain.PlatformCodeGenFlags"/>
   <valuelist type="QVariantList" key="ProjectExplorer.GccToolChain.PlatformLinkerFlags"/>
   <valuelist type="QVariantList" key="ProjectExplorer.GccToolChain.SupportedAbis">
    <value type="QString">x86-linux-generic-elf-64bit</value>
    <value type="QString">x86-linux-generic-elf-32bit</value>
   </valuelist>
   <value type="QString" key="ProjectExplorer.GccToolChain.TargetAbi">x86-linux-generic-elf-32bit</value>
   <value type="bool" key="ProjectExplorer.ToolChain.Autodetect">true</value>
   <value type="QString" key="ProjectExplorer.ToolChain.DisplayName">GCC (C++, x86 32bit in /usr/bin)</value>
   <value type="QString" key="ProjectExplorer.ToolChain.Id">ProjectExplorer.ToolChain.Gcc:{342ffe10-661c-4ed7-af4b-614b25f18928}</value>
   <value type="int" key="ProjectExplorer.ToolChain.Language">2</value>
   <value type="QString" key="ProjectExplorer.ToolChain.LanguageV2">Cxx</value>
  </valuemap>
 </data>
 <data>
  <variable>ToolChain.10</variable>
  <valuemap type="QVariantMap">
   <value type="QString" key="ProjectExplorer.GccToolChain.OriginalTargetTriple">x86_64-linux-gnu</value>
   <value type="QString" key="ProjectExplorer.GccToolChain.Path">/usr/bin/gcc-7</value>
   <valuelist type="QVariantList" key="ProjectExplorer.GccToolChain.PlatformCodeGenFlags"/>
   <valuelist type="QVariantList" key="ProjectExplorer.GccToolChain.PlatformLinkerFlags"/>
   <valuelist type="QVariantList" key="ProjectExplorer.GccToolChain.SupportedAbis">
    <value type="QString">x86-linux-generic-elf-64bit</value>
    <value type="QString">x86-linux-generic-elf-32bit</value>
   </valuelist>
   <value type="QString" key="ProjectExplorer.GccToolChain.TargetAbi">x86-linux-generic-elf-64bit</value>
   <value type="bool" key="ProjectExplorer.ToolChain.Autodetect">true</value>
   <value type="QString" key="ProjectExplorer.ToolChain.DisplayName">GCC 7 (C, x86 64bit in /usr/bin)</value>
   <value type="QString" key="ProjectExplorer.ToolChain.Id">ProjectExplorer.ToolChain.Gcc:{41dd7a42-b039-4ede-81b2-f7354866eed7}</value>
   <value type="int" key="ProjectExplorer.ToolChain.Language">1</value>
   <value type="QString" key="ProjectExplorer.ToolChain.LanguageV2">C</value>
  </valuemap>
 </data>
 <data>
  <variable>ToolChain.11</variable>
  <valuemap type="QVariantMap">
   <value type="QString" key="ProjectExplorer.GccToolChain.OriginalTargetTriple">x86_64-linux-gnu</value>
   <value type="QString" key="ProjectExplorer.GccToolChain.Path">/usr/bin/gcc-7</value>
   <valuelist type="QVariantList" key="ProjectExplorer.GccToolChain.PlatformCodeGenFlags"/>
   <valuelist type="QVariantList" key="ProjectExplorer.GccToolChain.PlatformLinkerFlags"/>
   <valuelist type="QVariantList" key="ProjectExplorer.GccToolChain.SupportedAbis">
    <value type="QString">x86-linux-generic-elf-64bit</value>
    <value type="QString">x86-linux-generic-elf-32bit</value>
   </valuelist>
   <value type="QString" key="ProjectExplorer.GccToolChain.TargetAbi">x86-linux-generic-elf-32bit</value>
   <value type="bool" key="ProjectExplorer.ToolChain.Autodetect">true</value>
   <value type="QString" key="ProjectExplorer.ToolChain.DisplayName">GCC 7 (C, x86 32bit in /usr/bin)</value>
   <value type="QString" key="ProjectExplorer.ToolChain.Id">ProjectExplorer.ToolChain.Gcc:{3f746646-af04-49ee-87ae-0ed457ee79f4}</value>
   <value type="int" key="ProjectExplorer.ToolChain.Language">1</value>
   <value type="QString" key="ProjectExplorer.ToolChain.LanguageV2">C</value>
  </valuemap>
 </data>
 <data>
  <variable>ToolChain.12</variable>
  <valuemap type="QVariantMap">
   <value type="QString" key="ProjectExplorer.GccToolChain.OriginalTargetTriple">x86_64-linux-gnu</value>
   <value type="QString" key="ProjectExplorer.GccToolChain.Path">/usr/bin/x86_64-linux-gnu-gcc</value>
   <valuelist type="QVariantList" key="ProjectExplorer.GccToolChain.PlatformCodeGenFlags"/>
   <valuelist type="QVariantList" key="ProjectExplorer.GccToolChain.PlatformLinkerFlags"/>
   <valuelist type="QVariantList" key="ProjectExplorer.GccToolChain.SupportedAbis">
    <value type="QString">x86-linux-generic-elf-64bit</value>
    <value type="QString">x86-linux-generic-elf-32bit</value>
   </valuelist>
   <value type="QString" key="ProjectExplorer.GccToolChain.TargetAbi">x86-linux-generic-elf-64bit</value>
   <value type="bool" key="ProjectExplorer.ToolChain.Autodetect">true</value>
   <value type="QString" key="ProjectExplorer.ToolChain.DisplayName">GCC (C, x86 64bit in /usr/bin)</value>
   <value type="QString" key="ProjectExplorer.ToolChain.Id">ProjectExplorer.ToolChain.Gcc:{c8a9eea0-8c8a-4511-920c-3f8da6d2f510}</value>
   <value type="int" key="ProjectExplorer.ToolChain.Language">1</value>
   <value type="QString" key="ProjectExplorer.ToolChain.LanguageV2">C</value>
  </valuemap>
 </data>
 <data>
  <variable>ToolChain.13</variable>
  <valuemap type="QVariantMap">
   <value type="QString" key="ProjectExplorer.GccToolChain.OriginalTargetTriple">x86_64-linux-gnu</value>
   <value type="QString" key="ProjectExplorer.GccToolChain.Path">/usr/bin/x86_64-linux-gnu-gcc</value>
   <valuelist type="QVariantList" key="ProjectExplorer.GccToolChain.PlatformCodeGenFlags"/>
   <valuelist type="QVariantList" key="ProjectExplorer.GccToolChain.PlatformLinkerFlags"/>
   <valuelist type="QVariantList" key="ProjectExplorer.GccToolChain.SupportedAbis">
    <value type="QString">x86-linux-generic-elf-64bit</value>
    <value type="QString">x86-linux-generic-elf-32bit</value>
   </valuelist>
   <value type="QString" key="ProjectExplorer.GccToolChain.TargetAbi">x86-linux-generic-elf-32bit</value>
   <value type="bool" key="ProjectExplorer.ToolChain.Autodetect">true</value>
   <value type="QString" key="ProjectExplorer.ToolChain.DisplayName">GCC (C, x86 32bit in /usr/bin)</value>
   <value type="QString" key="ProjectExplorer.ToolChain.Id">ProjectExplorer.ToolChain.Gcc:{caf29995-02f2-4346-86f0-1631fa90bd2f}</value>
   <value type="int" key="ProjectExplorer.ToolChain.Language">1</value>
   <value type="QString" key="ProjectExplorer.ToolChain.LanguageV2">C</value>
  </valuemap>
 </data>
 <data>
  <variable>ToolChain.14</variable>
  <valuemap type="QVariantMap">
   <value type="QString" key="ProjectExplorer.GccToolChain.OriginalTargetTriple">x86_64-linux-gnu</value>
   <value type="QString" key="ProjectExplorer.GccToolChain.Path">/usr/bin/x86_64-linux-gnu-gcc-7</value>
   <valuelist type="QVariantList" key="ProjectExplorer.GccToolChain.PlatformCodeGenFlags"/>
   <valuelist type="QVariantList" key="ProjectExplorer.GccToolChain.PlatformLinkerFlags"/>
   <valuelist type="QVariantList" key="ProjectExplorer.GccToolChain.SupportedAbis">
    <value type="QString">x86-linux-generic-elf-64bit</value>
    <value type="QString">x86-linux-generic-elf-32bit</value>
   </valuelist>
   <value type="QString" key="ProjectExplorer.GccToolChain.TargetAbi">x86-linux-generic-elf-64bit</value>
   <value type="bool" key="ProjectExplorer.ToolChain.Autodetect">true</value>
   <value type="QString" key="ProjectExplorer.ToolChain.DisplayName">GCC 7 (C, x86 64bit in /usr/bin)</value>
   <value type="QString" key="ProjectExplorer.ToolChain.Id">ProjectExplorer.ToolChain.Gcc:{a3dbae06-9244-4232-9d93-95f196f67880}</value>
   <value type="int" key="ProjectExplorer.ToolChain.Language">1</value>
   <value type="QString" key="ProjectExplorer.ToolChain.LanguageV2">C</value>
  </valuemap>
 </data>
 <data>
  <variable>ToolChain.15</variable>
  <valuemap type="QVariantMap">
   <value type="QString" key="ProjectExplorer.GccToolChain.OriginalTargetTriple">x86_64-linux-gnu</value>
   <value type="QString" key="ProjectExplorer.GccToolChain.Path">/usr/bin/x86_64-linux-gnu-gcc-7</value>
   <valuelist type="QVariantList" key="ProjectExplorer.GccToolChain.PlatformCodeGenFlags"/>
   <valuelist type="QVariantList" key="ProjectExplorer.GccToolChain.PlatformLinkerFlags"/>
   <valuelist type="QVariantList" key="ProjectExplorer.GccToolChain.SupportedAbis">
    <value type="QString">x86-linux-generic-elf-64bit</value>
    <value type="QString">x86-linux-generic-elf-32bit</value>
   </valuelist>
   <value type="QString" key="ProjectExplorer.GccToolChain.TargetAbi">x86-linux-generic-elf-32bit</value>
   <value type="bool" key="ProjectExplorer.ToolChain.Autodetect">true</value>
   <value type="QString" key="ProjectExplorer.ToolChain.DisplayName">GCC 7 (C, x86 32bit in /usr/bin)</value>
   <value type="QString" key="ProjectExplorer.ToolChain.Id">ProjectExplorer.ToolChain.Gcc:{d078c391-bba1-4d4a-aee8-e9dd24c45e37}</value>
   <value type="int" key="ProjectExplorer.ToolChain.Language">1</value>
   <value type="QString" key="ProjectExplorer.ToolChain.LanguageV2">C</value>
  </valuemap>
 </data>
 <data>
  <variable>ToolChain.16</variable>
  <valuemap type="QVariantMap">
   <value type="QString" key="ProjectExplorer.GccToolChain.OriginalTargetTriple">x86_64-pc-linux-gnu</value>
   <value type="QString" key="ProjectExplorer.GccToolChain.Path">/usr/bin/clang++</value>
   <valuelist type="QVariantList" key="ProjectExplorer.GccToolChain.PlatformCodeGenFlags"/>
   <valuelist type="QVariantList" key="ProjectExplorer.GccToolChain.PlatformLinkerFlags"/>
   <valuelist type="QVariantList" key="ProjectExplorer.GccToolChain.SupportedAbis">
    <value type="QString">x86-linux-generic-elf-64bit</value>
    <value type="QString">x86-linux-generic-elf-32bit</value>
   </valuelist>
   <value type="QString" key="ProjectExplorer.GccToolChain.TargetAbi">x86-linux-generic-elf-64bit</value>
   <value type="bool" key="ProjectExplorer.ToolChain.Autodetect">true</value>
   <value type="QString" key="ProjectExplorer.ToolChain.DisplayName">Clang (C++, x86 64bit in /usr/bin)</value>
   <value type="QString" key="ProjectExplorer.ToolChain.Id">ProjectExplorer.ToolChain.Clang:{8e9f720d-752d-43d9-9b10-dc95e4504adf}</value>
   <value type="int" key="ProjectExplorer.ToolChain.Language">2</value>
   <value type="QString" key="ProjectExplorer.ToolChain.LanguageV2">Cxx</value>
  </valuemap>
 </data>
 <data>
  <variable>ToolChain.17</variable>
  <valuemap type="QVariantMap">
   <value type="QString" key="ProjectExplorer.GccToolChain.OriginalTargetTriple">x86_64-pc-linux-gnu</value>
   <value type="QString" key="ProjectExplorer.GccToolChain.Path">/usr/bin/clang++</value>
   <valuelist type="QVariantList" key="ProjectExplorer.GccToolChain.PlatformCodeGenFlags"/>
   <valuelist type="QVariantList" key="ProjectExplorer.GccToolChain.PlatformLinkerFlags"/>
   <valuelist type="QVariantList" key="ProjectExplorer.GccToolChain.SupportedAbis">
    <value type="QString">x86-linux-generic-elf-64bit</value>
    <value type="QString">x86-linux-generic-elf-32bit</value>
   </valuelist>
   <value type="QString" key="ProjectExplorer.GccToolChain.TargetAbi">x86-linux-generic-elf-32bit</value>
   <value type="bool" key="ProjectExplorer.ToolChain.Autodetect">true</value>
   <value type="QString" key="ProjectExplorer.ToolChain.DisplayName">Clang (C++, x86 32bit in /usr/bin)</value>
   <value type="QString" key="ProjectExplorer.ToolChain.Id">ProjectExplorer.ToolChain.Clang:{9dcc08bf-3a86-462b-ad65-6c611b19a096}</value>
   <value type="int" key="ProjectExplorer.ToolChain.Language">2</value>
   <value type="QString" key="ProjectExplorer.ToolChain.LanguageV2">Cxx</value>
  </valuemap>
 </data>
 <data>
  <variable>ToolChain.18</variable>
  <valuemap type="QVariantMap">
   <value type="QString" key="ProjectExplorer.GccToolChain.OriginalTargetTriple">x86_64-pc-linux-gnu</value>
   <value type="QString" key="ProjectExplorer.GccToolChain.Path">/usr/bin/clang</value>
   <valuelist type="QVariantList" key="ProjectExplorer.GccToolChain.PlatformCodeGenFlags"/>
   <valuelist type="QVariantList" key="ProjectExplorer.GccToolChain.PlatformLinkerFlags"/>
   <valuelist type="QVariantList" key="ProjectExplorer.GccToolChain.SupportedAbis">
    <value type="QString">x86-linux-generic-elf-64bit</value>
    <value type="QString">x86-linux-generic-elf-32bit</value>
   </valuelist>
   <value type="QString" key="ProjectExplorer.GccToolChain.TargetAbi">x86-linux-generic-elf-64bit</value>
   <value type="bool" key="ProjectExplorer.ToolChain.Autodetect">true</value>
   <value type="QString" key="ProjectExplorer.ToolChain.DisplayName">Clang (C, x86 64bit in /usr/bin)</value>
   <value type="QString" key="ProjectExplorer.ToolChain.Id">ProjectExplorer.ToolChain.Clang:{10543bb9-48ba-453b-835f-c50d35f70bb8}</value>
   <value type="int" key="ProjectExplorer.ToolChain.Language">1</value>
   <value type="QString" key="ProjectExplorer.ToolChain.LanguageV2">C</value>
  </valuemap>
 </data>
 <data>
  <variable>ToolChain.19</variable>
  <valuemap type="QVariantMap">
   <value type="QString" key="ProjectExplorer.GccToolChain.OriginalTargetTriple">x86_64-pc-linux-gnu</value>
   <value type="QString" key="ProjectExplorer.GccToolChain.Path">/usr/bin/clang</value>
   <valuelist type="QVariantList" key="ProjectExplorer.GccToolChain.PlatformCodeGenFlags"/>
   <valuelist type="QVariantList" key="ProjectExplorer.GccToolChain.PlatformLinkerFlags"/>
   <valuelist type="QVariantList" key="ProjectExplorer.GccToolChain.SupportedAbis">
    <value type="QString">x86-linux-generic-elf-64bit</value>
    <value type="QString">x86-linux-generic-elf-32bit</value>
   </valuelist>
   <value type="QString" key="ProjectExplorer.GccToolChain.TargetAbi">x86-linux-generic-elf-32bit</value>
   <value type="bool" key="ProjectExplorer.ToolChain.Autodetect">true</value>
   <value type="QString" key="ProjectExplorer.ToolChain.DisplayName">Clang (C, x86 32bit in /usr/bin)</value>
   <value type="QString" key="ProjectExplorer.ToolChain.Id">ProjectExplorer.ToolChain.Clang:{cce4d507-b898-455d-92eb-80e102fa2f0c}</value>
   <value type="int" key="ProjectExplorer.ToolChain.Language">1</value>
   <value type="QString" key="ProjectExplorer.ToolChain.LanguageV2">C</value>
  </valuemap>
 </data>
 <data>
  <variable>ToolChain.2</variable>
  <valuemap type="QVariantMap">
   <value type="QString" key="ProjectExplorer.GccToolChain.OriginalTargetTriple">x86_64-linux-gnu</value>
   <value type="QString" key="ProjectExplorer.GccToolChain.Path">/usr/bin/gcc</value>
   <valuelist type="QVariantList" key="ProjectExplorer.GccToolChain.PlatformCodeGenFlags"/>
   <valuelist type="QVariantList" key="ProjectExplorer.GccToolChain.PlatformLinkerFlags"/>
   <valuelist type="QVariantList" key="ProjectExplorer.GccToolChain.SupportedAbis">
    <value type="QString">x86-linux-generic-elf-64bit</value>
    <value type="QString">x86-linux-generic-elf-32bit</value>
   </valuelist>
   <value type="QString" key="ProjectExplorer.GccToolChain.TargetAbi">x86-linux-generic-elf-64bit</value>
   <value type="bool" key="ProjectExplorer.ToolChain.Autodetect">true</value>
   <value type="QString" key="ProjectExplorer.ToolChain.DisplayName">GCC (C, x86 64bit in /usr/bin)</value>
   <value type="QString" key="ProjectExplorer.ToolChain.Id">ProjectExplorer.ToolChain.Gcc:{59e4d38a-4072-413f-be75-62ca94140369}</value>
   <value type="int" key="ProjectExplorer.ToolChain.Language">1</value>
   <value type="QString" key="ProjectExplorer.ToolChain.LanguageV2">C</value>
  </valuemap>
 </data>
 <data>
  <variable>ToolChain.3</variable>
  <valuemap type="QVariantMap">
   <value type="QString" key="ProjectExplorer.GccToolChain.OriginalTargetTriple">x86_64-linux-gnu</value>
   <value type="QString" key="ProjectExplorer.GccToolChain.Path">/usr/bin/gcc</value>
   <valuelist type="QVariantList" key="ProjectExplorer.GccToolChain.PlatformCodeGenFlags"/>
   <valuelist type="QVariantList" key="ProjectExplorer.GccToolChain.PlatformLinkerFlags"/>
   <valuelist type="QVariantList" key="ProjectExplorer.GccToolChain.SupportedAbis">
    <value type="QString">x86-linux-generic-elf-64bit</value>
    <value type="QString">x86-linux-generic-elf-32bit</value>
   </valuelist>
   <value type="QString" key="ProjectExplorer.GccToolChain.TargetAbi">x86-linux-generic-elf-32bit</value>
   <value type="bool" key="ProjectExplorer.ToolChain.Autodetect">true</value>
   <value type="QString" key="ProjectExplorer.ToolChain.DisplayName">GCC (C, x86 32bit in /usr/bin)</value>
   <value type="QString" key="ProjectExplorer.ToolChain.Id">ProjectExplorer.ToolChain.Gcc:{f9dbc74c-1e9c-4dfe-ad5f-7125a5770034}</value>
   <value type="int" key="ProjectExplorer.ToolChain.Language">1</value>
   <value type="QString" key="ProjectExplorer.ToolChain.LanguageV2">C</value>
  </valuemap>
 </data>
 <data>
  <variable>ToolChain.4</variable>
  <valuemap type="QVariantMap">
   <value type="QString" key="ProjectExplorer.GccToolChain.OriginalTargetTriple">x86_64-linux-gnu</value>
   <value type="QString" key="ProjectExplorer.GccToolChain.Path">/usr/bin/g++-7</value>
   <valuelist type="QVariantList" key="ProjectExplorer.GccToolChain.PlatformCodeGenFlags"/>
   <valuelist type="QVariantList" key="ProjectExplorer.GccToolChain.PlatformLinkerFlags"/>
   <valuelist type="QVariantList" key="ProjectExplorer.GccToolChain.SupportedAbis">
    <value type="QString">x86-linux-generic-elf-64bit</value>
    <value type="QString">x86-linux-generic-elf-32bit</value>
   </valuelist>
   <value type="QString" key="ProjectExplorer.GccToolChain.TargetAbi">x86-linux-generic-elf-64bit</value>
   <value type="bool" key="ProjectExplorer.ToolChain.Autodetect">true</value>
   <value type="QString" key="ProjectExplorer.ToolChain.DisplayName">GCC 7 (C++, x86 64bit in /usr/bin)</value>
   <value type="QString" key="ProjectExplorer.ToolChain.Id">ProjectExplorer.ToolChain.Gcc:{22af8f84-1cdf-4bd9-ba3a-f64523e707ed}</value>
   <value type="int" key="ProjectExplorer.ToolChain.Language">2</value>
   <value type="QString" key="ProjectExplorer.ToolChain.LanguageV2">Cxx</value>
  </valuemap>
 </data>
 <data>
  <variable>ToolChain.5</variable>
  <valuemap type="QVariantMap">
   <value type="QString" key="ProjectExplorer.GccToolChain.OriginalTargetTriple">x86_64-linux-gnu</value>
   <value type="QString" key="ProjectExplorer.GccToolChain.Path">/usr/bin/g++-7</value>
   <valuelist type="QVariantList" key="ProjectExplorer.GccToolChain.PlatformCodeGenFlags"/>
   <valuelist type="QVariantList" key="ProjectExplorer.GccToolChain.PlatformLinkerFlags"/>
   <valuelist type="QVariantList" key="ProjectExplorer.GccToolChain.SupportedAbis">
    <value type="QString">x86-linux-generic-elf-64bit</value>
    <value type="QString">x86-linux-generic-elf-32bit</value>
   </valuelist>
   <value type="QString" key="ProjectExplorer.GccToolChain.TargetAbi">x86-linux-generic-elf-32bit</value>
   <value type="bool" key="ProjectExplorer.ToolChain.Autodetect">true</value>
   <value type="QString" key="ProjectExplorer.ToolChain.DisplayName">GCC 7 (C++, x86 32bit in /usr/bin)</value>
   <value type="QString" key="ProjectExplorer.ToolChain.Id">ProjectExplorer.ToolChain.Gcc:{067ed59c-392b-4f84-9d66-eb5f0e0f9352}</value>
   <value type="int" key="ProjectExplorer.ToolChain.Language">2</value>
   <value type="QString" key="ProjectExplorer.ToolChain.LanguageV2">Cxx</value>
  </valuemap>
 </data>
 <data>
  <variable>ToolChain.6</variable>
  <valuemap type="QVariantMap">
   <value type="QString" key="ProjectExplorer.GccToolChain.OriginalTargetTriple">x86_64-linux-gnu</value>
   <value type="QString" key="ProjectExplorer.GccToolChain.Path">/usr/bin/x86_64-linux-gnu-g++</value>
   <valuelist type="QVariantList" key="ProjectExplorer.GccToolChain.PlatformCodeGenFlags"/>
   <valuelist type="QVariantList" key="ProjectExplorer.GccToolChain.PlatformLinkerFlags"/>
   <valuelist type="QVariantList" key="ProjectExplorer.GccToolChain.SupportedAbis">
    <value type="QString">x86-linux-generic-elf-64bit</value>
    <value type="QString">x86-linux-generic-elf-32bit</value>
   </valuelist>
   <value type="QString" key="ProjectExplorer.GccToolChain.TargetAbi">x86-linux-generic-elf-64bit</value>
   <value type="bool" key="ProjectExplorer.ToolChain.Autodetect">true</value>
   <value type="QString" key="ProjectExplorer.ToolChain.DisplayName">GCC (C++, x86 64bit in /usr/bin)</value>
   <value type="QString" key="ProjectExplorer.ToolChain.Id">ProjectExplorer.ToolChain.Gcc:{c3761404-0693-448c-b99d-1ed5c2f1493b}</value>
   <value type="int" key="ProjectExplorer.ToolChain.Language">2</value>
   <value type="QString" key="ProjectExplorer.ToolChain.LanguageV2">Cxx</value>
  </valuemap>
 </data>
 <data>
  <variable>ToolChain.7</variable>
  <valuemap type="QVariantMap">
   <value type="QString" key="ProjectExplorer.GccToolChain.OriginalTargetTriple">x86_64-linux-gnu</value>
   <value type="QString" key="ProjectExplorer.GccToolChain.Path">/usr/bin/x86_64-linux-gnu-g++</value>
   <valuelist type="QVariantList" key="ProjectExplorer.GccToolChain.PlatformCodeGenFlags"/>
   <valuelist type="QVariantList" key="ProjectExplorer.GccToolChain.PlatformLinkerFlags"/>
   <valuelist type="QVariantList" key="ProjectExplorer.GccToolChain.SupportedAbis">
    <value type="QString">x86-linux-generic-elf-64bit</value>
    <value type="QString">x86-linux-generic-elf-32bit</value>
   </valuelist>
   <value type="QString" key="ProjectExplorer.GccToolChain.TargetAbi">x86-linux-generic-elf-32bit</value>
   <value type="bool" key="ProjectExplorer.ToolChain.Autodetect">true</value>
   <value type="QString" key="ProjectExplorer.ToolChain.DisplayName">GCC (C++, x86 32bit in /usr/bin)</value>
   <value type="QString" key="ProjectExplorer.ToolChain.Id">ProjectExplorer.ToolChain.Gcc:{b03c0e97-d92f-4bfe-bd1b-9cbef63c4e25}</value>
   <value type="int" key="ProjectExplorer.ToolChain.Language">2</value>
   <value type="QString" key="ProjectExplorer.ToolChain.LanguageV2">Cxx</value>
  </valuemap>
 </data>
 <data>
  <variable>ToolChain.8</variable>
  <valuemap type="QVariantMap">
   <value type="QString" key="ProjectExplorer.GccToolChain.OriginalTargetTriple">x86_64-linux-gnu</value>
   <value type="QString" key="ProjectExplorer.GccToolChain.Path">/usr/bin/x86_64-linux-gnu-g++-7</value>
   <valuelist type="QVariantList" key="ProjectExplorer.GccToolChain.PlatformCodeGenFlags"/>
   <valuelist type="QVariantList" key="ProjectExplorer.GccToolChain.PlatformLinkerFlags"/>
   <valuelist type="QVariantList" key="ProjectExplorer.GccToolChain.SupportedAbis">
    <value type="QString">x86-linux-generic-elf-64bit</value>
    <value type="QString">x86-linux-generic-elf-32bit</value>
   </valuelist>
   <value type="QString" key="ProjectExplorer.GccToolChain.TargetAbi">x86-linux-generic-elf-64bit</value>
   <value type="bool" key="ProjectExplorer.ToolChain.Autodetect">true</value>
   <value type="QString" key="ProjectExplorer.ToolChain.DisplayName">GCC 7 (C++, x86 64bit in /usr/bin)</value>
   <value type="QString" key="ProjectExplorer.ToolChain.Id">ProjectExplorer.ToolChain.Gcc:{ca184268-edfb-4905-933d-429bc773b70c}</value>
   <value type="int" key="ProjectExplorer.ToolChain.Language">2</value>
   <value type="QString" key="ProjectExplorer.ToolChain.LanguageV2">Cxx</value>
  </valuemap>
 </data>
 <data>
  <variable>ToolChain.9</variable>
  <valuemap type="QVariantMap">
   <value type="QString" key="ProjectExplorer.GccToolChain.OriginalTargetTriple">x86_64-linux-gnu</value>
   <value type="QString" key="ProjectExplorer.GccToolChain.Path">/usr/bin/x86_64-linux-gnu-g++-7</value>
   <valuelist type="QVariantList" key="ProjectExplorer.GccToolChain.PlatformCodeGenFlags"/>
   <valuelist type="QVariantList" key="ProjectExplorer.GccToolChain.PlatformLinkerFlags"/>
   <valuelist type="QVariantList" key="ProjectExplorer.GccToolChain.SupportedAbis">
    <value type="QString">x86-linux-generic-elf-64bit</value>
    <value type="QString">x86-linux-generic-elf-32bit</value>
   </valuelist>
   <value type="QString" key="ProjectExplorer.GccToolChain.TargetAbi">x86-linux-generic-elf-32bit</value>
   <value type="bool" key="ProjectExplorer.ToolChain.Autodetect">true</value>
   <value type="QString" key="ProjectExplorer.ToolChain.DisplayName">GCC 7 (C++, x86 32bit in /usr/bin)</value>
   <value type="QString" key="ProjectExplorer.ToolChain.Id">ProjectExplorer.ToolChain.Gcc:{e1b7ec49-a767-40ed-9734-3085a2a930ba}</value>
   <value type="int" key="ProjectExplorer.ToolChain.Language">2</value>
   <value type="QString" key="ProjectExplorer.ToolChain.LanguageV2">Cxx</value>
  </valuemap>
 </data>
 <data>
  <variable>ToolChain.Count</variable>
  <value type="int">20</value>
 </data>
 <data>
  <variable>Version</variable>
  <value type="int">1</value>
 </data>
</qtcreator>
